clingodl/__init__.py
clingodl/__main__.py
clingodl/_clingodl.cp36-win_amd64.pyd
clingodl/clingo-dl.h
clingodl/import__clingodl.lib
clingodl/py.typed
clingo_dl-1.5.0.post1.dist-info/LICENSE.md
clingo_dl-1.5.0.post1.dist-info/METADATA
clingo_dl-1.5.0.post1.dist-info/WHEEL
clingo_dl-1.5.0.post1.dist-info/top_level.txt
clingo_dl-1.5.0.post1.dist-info/RECORD
