Metadata-Version: 2.1
Name: clingo-dl
Version: 1.5.0.post1
Summary: CFFI-based bindings to the clingo-dl solver.
Home-page: https://github.com/potassco/clingo-dl
Author: Roland Kaminski
Author-email: kaminski@cs.uni-potsdam.de
License: MIT
Platform: UNKNOWN
Requires-Python: >=3.6
License-File: LICENSE.md
Requires-Dist: cffi
Requires-Dist: clingo
